program_counter.v
module program_counter(
    input clk,
    input rst,
    input [7:0] next_pc,
    output reg [7:0] pc
);
    always @(posedge clk or posedge rst) begin
        if (rst)
            pc <= 8'b0;
        else
            pc <= next_pc;
    end
endmodule

program_counter_tb.v
`timescale 1ns / 1ps

module program_counter_tb;

    // Inputs
    reg clk;
    reg rst;
    reg [7:0] next_pc;

    // Output
    wire [7:0] pc;

    // Instantiate the Unit Under Test (UUT)
    program_counter uut (
        .clk(clk),
        .rst(rst),
        .next_pc(next_pc),
        .pc(pc)
    );

    // Clock generation (10 ns period)
    initial begin
        clk = 0;
        forever #5 clk = ~clk;
    end

    // Test sequence
    initial begin

        // Initialize inputs
        rst = 1; next_pc = 8'h00;
        #10; // Apply reset
        rst = 0;

        // Apply a sequence of values
        next_pc = 8'h05; #10;
        next_pc = 8'h0A; #10;
        next_pc = 8'hFF; #10;

        // Apply reset again
        rst = 1; #10;
        rst = 0; next_pc = 8'h11; #10;

        // Finish simulation
        $stop;
    end
initial begin
    $dumpfile("pc.vcd");
    $dumpvars(0, program_counter_tb);
end

endmodule

sim/pc.vcd
$date
	Sun Jul  6 08:49:20 2025
$end
$version
	Icarus Verilog
$end
$timescale
	1ps
$end
$scope module program_counter_tb $end
$var wire 8 ! pc [7:0] $end
$var reg 1 " clk $end
$var reg 8 # next_pc [7:0] $end
$var reg 1 $ rst $end
$scope module uut $end
$var wire 1 " clk $end
$var wire 8 % next_pc [7:0] $end
$var wire 1 $ rst $end
$var reg 8 & pc [7:0] $end
$upscope $end
$upscope $end
$enddefinitions $end
$comment Show the parameter values. $end
$dumpall
$end
#0
$dumpvars
b0 &
b0 %
1$
b0 #
0"
b0 !
$end
#5000
1"
#10000
0"
b101 #
b101 %
0$
#15000
b101 !
b101 &
1"
#20000
0"
b1010 #
b1010 %
#25000
b1010 !
b1010 &
1"
#30000
0"
b11111111 #
b11111111 %
#35000
b11111111 !
b11111111 &
1"
#40000
b0 !
b0 &
0"
1$
#45000
1"
#50000
0"
b10001 #
b10001 %
0$
#55000
b10001 !
b10001 &
1"
